dagster_nomad/__init__.py
dagster_nomad/__version__.py
dagster_nomad/run_launcher.py
dagster_nomad_test/conftest.py
dagster_nomad_test/test_run_launcher.py
dagster_nomad-0.0.3.dist-info/METADATA
dagster_nomad-0.0.3.dist-info/WHEEL
dagster_nomad-0.0.3.dist-info/top_level.txt
dagster_nomad-0.0.3.dist-info/RECORD
